Apfloat/apfloat.py
Apfloat/apfloat_tests.py
Apfloat/apfloat_versus_mpf.py
Apfloat-1.1.dist-info/LICENSE
Apfloat-1.1.dist-info/METADATA
Apfloat-1.1.dist-info/WHEEL
Apfloat-1.1.dist-info/entry_points.txt
Apfloat-1.1.dist-info/top_level.txt
Apfloat-1.1.dist-info/RECORD
