Metadata-Version: 2.1
Name: Apfloat
Version: 1.1
Summary: This package contains implementation of the library "Apfloat". Apfloat is a data type supporting arbitrary-precision numbers.
Home-page: https://github.com/DigitalCreativeApkDev/Apfloat
Author: DigitalCreativeApkDev
Author-email: digitalcreativeapkdev2022@gmail.com
License: MIT
Platform: UNKNOWN
Classifier: Programming Language :: Python :: 3
Classifier: Programming Language :: Python :: 3.7
